qanapi/__init__.py
qanapi/_base_client.py
qanapi/_client.py
qanapi/_compat.py
qanapi/_constants.py
qanapi/_exceptions.py
qanapi/_files.py
qanapi/_models.py
qanapi/_qs.py
qanapi/_resource.py
qanapi/_response.py
qanapi/_streaming.py
qanapi/_types.py
qanapi/_version.py
qanapi/py.typed
qanapi/_utils/__init__.py
qanapi/_utils/_logs.py
qanapi/_utils/_proxy.py
qanapi/_utils/_reflection.py
qanapi/_utils/_resources_proxy.py
qanapi/_utils/_streams.py
qanapi/_utils/_sync.py
qanapi/_utils/_transform.py
qanapi/_utils/_typing.py
qanapi/_utils/_utils.py
qanapi/lib/.keep
qanapi/resources/__init__.py
qanapi/resources/auth.py
qanapi/resources/decrypt.py
qanapi/resources/encrypt.py
qanapi/resources/scopes.py
qanapi/resources/api_keys/__init__.py
qanapi/resources/api_keys/api_keys.py
qanapi/resources/api_keys/scopes.py
qanapi/types/__init__.py
qanapi/types/api_key_revoke_response.py
qanapi/types/api_key_rotate_response.py
qanapi/types/auth_login_params.py
qanapi/types/auth_login_response.py
qanapi/types/auth_logout_response.py
qanapi/types/auth_refresh_token_response.py
qanapi/types/auth_retrieve_user_details_response.py
qanapi/types/auth_revoke_token_response.py
qanapi/types/decrypt_decrypt_payload_params.py
qanapi/types/decrypt_decrypt_payload_response.py
qanapi/types/encrypt_encrypt_data_params.py
qanapi/types/encrypt_encrypt_data_response.py
qanapi/types/scope_create_params.py
qanapi/types/scope_create_response.py
qanapi/types/scope_delete_response.py
qanapi/types/scope_list_response.py
qanapi/types/scope_retrieve_response.py
qanapi/types/scope_update_params.py
qanapi/types/scope_update_response.py
qanapi/types/api_keys/__init__.py
qanapi/types/api_keys/scope_attach_params.py
qanapi/types/api_keys/scope_attach_response.py
qanapi/types/api_keys/scope_detach_params.py
qanapi/types/api_keys/scope_detach_response.py
qanapi/types/api_keys/scope_retrieve_response.py
qanapi/types/api_keys/scope_sync_params.py
qanapi/types/api_keys/scope_sync_response.py
qanapi-1.1.0.dist-info/METADATA
qanapi-1.1.0.dist-info/WHEEL
qanapi-1.1.0.dist-info/licenses/LICENSE
qanapi-1.1.0.dist-info/RECORD
